Workbook

Sheet Survival 200
A1: No | B1: Situasi | C1: Indonesia | D1: Pinyin | E1: Hanzi | F1: Arti per kata | G1: Keterangan | H1: Status
A2: 1 | B2: Tidak mengerti & minta bantuan | C2: Saya tidak mengerti | D2: Wǒ tīng bu dǒng | E2: 我听不懂 | F2: 我 (wǒ): saya, 听 (tīng): dengar, 不 (bu): tidak, 懂 (dǒng): paham | G2: Kalimat paling penting minggu 1 | H2: Belum
A3: 2 | B3: Tidak mengerti & minta bantuan | C3: Saya tidak mengerti | D3: Wǒ bù dǒng | E3: 我不懂 | F3: 我 (wǒ): saya, 不 (bù): tidak, 懂 (dǒng): mengerti
A4: 3 | B4: Tidak mengerti & minta bantuan | C4: Saya mengerti | D4: Wǒ tīng dǒng le | E4: 我听懂了 | F4: 听 (tīng): dengar, 懂 (dǒng): paham, 了 (le): partikel selesai | H4: Belum
A5: 4 | B5: Tidak mengerti & minta bantuan | C5: Saya mengerti | D5: Wǒ dǒng le | E5: 我懂了 | F5: 我 (wǒ): saya, 懂 (dǒng): mengerti, 了 (le): partikel selesai
A6: 5 | B6: Tidak mengerti & minta bantuan | C6: Tolong bantu saya | D6: Qǐng bāngbang wǒ | E6: 请帮帮我 | F6: 请 (qǐng): tolong, 帮帮 (bāngbang): bantu (bentuk ulang, lebih halus), 我 (wǒ): saya | H6: Belum
A7: 6 | B7: Tidak mengerti & minta bantuan | C7: Tolong bantu saya | D7: Bāng wǒ | E7: 帮我 | F7: 帮 (bāng): bantu, 我 (wǒ): saya | G7: Lebih sopan: 请帮我 qǐng bāng wǒ
A8: 7 | B8: Angka & waktu | C8: Jam berapa sekarang? | D8: Xiànzài jǐ diǎn? | E8: 现在几点？ | F8: 现在 (xiànzài): sekarang, 几 (jǐ): berapa, 点 (diǎn): jam | H8: Belum
A9: 8 | B9: Angka & waktu | C9: Jam berapa sekarang? | D9: Xiànzài jǐ diǎn le? | E9: 现在几点了？ | F9: 现在 (xiànzài): sekarang, 几 (jǐ): berapa, 点 (diǎn): jam, 了 (le): partikel
A10: 9 | B10: Belanja & pembayaran | C10: Berapa harganya? | D10: Zhège duōshao qián? | E10: 这个多少钱？ | F10: 这个 (zhège): ini, 多少 (duōshao): berapa, 钱 (qián): uang / harga | H10: Belum
A11: 10 | B11: Belanja & pembayaran | C11: Berapa harganya? | D11: Duōshao qián? | E11: 多少钱？ | F11: 多少 (duōshao): berapa, 钱 (qián): uang / harga | G11: Pinyin dikoreksi dari "duìshǎo qián"
A12: 11 | B12: Tidak mengerti & minta bantuan | C12: Saya kurang begitu / tidak begitu paham / mengerti | D12: Wǒ bù tài lǐjiě | E12: 我不太理解 | F12: 我 (wǒ): saya, 不 (bù): tidak, 太 (tài): terlalu, 理解 (lǐjiě): mengerti
A13: 12 | B13: Tidak mengerti & minta bantuan | C13: Saya kurang begitu / tidak begitu paham / mengerti | D13: Wǒ bú tài míngbái | E13: 我不太明白 | F13: 我 (wǒ): saya, 不 (bú): tidak, 太 (tài): terlalu, 明白 (míngbái): paham
A14: 13 | B14: Angka & waktu | C14: Dua puluh (20) | D14: Èrshí | E14: 二十 | F14: 二 (èr): dua, 十 (shí): sepuluh
A15: 14 | B15: Angka & waktu | C15: Seratus (100) | D15: Yìbǎi | E15: 一百 | F15: 一 (yī): satu, 百 (bǎi): ratus
A16: 15 | B16: Angka & waktu | C16: Dua orang | D16: Liǎng ge rén | E16: 两个人 | F16: 两 (liǎng): dua, 个 (ge): kata penggolong, 人 (rén): orang | G16: Untuk jumlah/penggolong pakai 两, bukan 二 | H16: Belum
A17: 16 | B17: Angka & waktu | C17: Hari ini hari apa? | D17: Jīntiān xīngqī jǐ? | E17: 今天星期几？ | F17: 今天 (jīntiān): hari ini, 星期 (xīngqī): hari dalam minggu, 几 (jǐ): berapa | H17: Belum
A18: 17 | B18: Angka & waktu | C18: Hari ini tanggal berapa? | D18: Jīntiān jǐ hào? | E18: 今天几号？ | F18: 今天 (jīntiān): hari ini, 几 (jǐ): berapa, 号 (hào): tanggal | H18: Belum
A19: 18 | B19: Angka & waktu | C19: Satu, dua, tiga, empat, lima | D19: Yī, èr, sān, sì, wǔ | E19: 一、二、三、四、五 | F19: 一 (yī): satu, 二 (èr): dua, 三 (sān): tiga, 四 (sì): empat, 五 (wǔ): lima | H19: Belum
A20: 19 | B20: Angka & waktu | C20: Enam, tujuh, delapan, sembilan, sepuluh | D20: Liù, qī, bā, jiǔ, shí | E20: 六、七、八、九、十 | F20: 六 (liù): enam, 七 (qī): tujuh, 八 (bā): delapan, 九 (jiǔ): sembilan, 十 (shí): sepuluh | H20: Belum
A21: 20 | B21: Angka & waktu | C21: Jam delapan | D21: Bā diǎn | E21: 八点 | F21: 八 (bā): delapan, 点 (diǎn): jam | H21: Belum
A22: 21 | B22: Angka & waktu | C22: Besok jam sembilan | D22: Míngtiān jiǔ diǎn | E22: 明天九点 | F22: 明天 (míngtiān): besok, 九 (jiǔ): sembilan, 点 (diǎn): jam | H22: Belum
A23: 22 | B23: Angka & waktu | C23: Agustus | D23: Bāyuè | E23: 八月 | F23: 八 (bā): delapan, 月 (yuè): bulan
A24: 23 | B24: Angka & waktu | C24: April | D24: Sìyuè | E24: 四月 | F24: 四 (sì): empat, 月 (yuè): bulan
A25: 24 | B25: Angka & waktu | C25: Besok | D25: Míngtiān | E25: 明天 | F25: 明 (míng): esok, 天 (tiān): hari, 明天 (míngtiān): besok
A26: 25 | B26: Angka & waktu | C26: Bulan depan | D26: Xià ge yuè | E26: 下个月 | F26: 下 (xià): berikutnya, 个 (gè): kata penggolong, 月 (yuè): bulan
A27: 26 | B27: Angka & waktu | C27: Delapan | D27: Bā | E27: 八 | F27: 八 (bā): delapan
A28: 27 | B28: Angka & waktu | C28: Desember | D28: Shí'èryuè | E28: 十二月 | F28: 十二 (shí'èr): dua belas, 月 (yuè): bulan
A29: 28 | B29: Angka & waktu | C29: Dua | D29: Èr | E29: 二 | F29: 二 (èr): dua
A30: 29 | B30: Angka & waktu | C30: Dua belas | D30: Shí'èr | E30: 十二 | F30: 十 (shí): sepuluh, 二 (èr): dua
A31: 30 | B31: Angka & waktu | C31: Empat | D31: Sì | E31: 四 | F31: 四 (sì): empat
A32: 31 | B32: Angka & waktu | C32: Empat belas | D32: Shísì | E32: 十四 | F32: 十 (shí): sepuluh, 四 (sì): empat
A33: 32 | B33: Angka & waktu | C33: Enam | D33: Liù | E33: 六 | F33: 六 (liù): enam
A34: 33 | B34: Angka & waktu | C34: Februari | D34: Èryuè | E34: 二月 | F34: 二 (èr): dua, 月 (yuè): bulan | G34: Pada kolom B tertulis "Fabruari" → seharusnya "Februari"
A35: 34 | B35: Angka & waktu | C35: Hari ini | D35: Jīntiān | E35: 今天 | F35: 今天 (jīntiān): hari ini
A36: 35 | B36: Angka & waktu | C36: Januari | D36: Yīyuè | E36: 一月 | F36: 一 (yī): satu, 月 (yuè): bulan | G36: Nama bulan = angka + 月
A37: 36 | B37: Angka & waktu | C37: Juli | D37: Qīyuè | E37: 七月 | F37: 七 (qī): tujuh, 月 (yuè): bulan
A38: 37 | B38: Angka & waktu | C38: Jumat | D38: Xīngqīwǔ | E38: 星期五 | F38: 星期 (xīngqī): minggu / hari, 五 (wǔ): lima
A39: 38 | B39: Angka & waktu | C39: Juni | D39: Liùyuè | E39: 六月 | F39: 六 (liù): enam, 月 (yuè): bulan
A40: 39 | B40: Angka & waktu | C40: Kamis | D40: Xīngqīsì | E40: 星期四 | F40: 星期 (xīngqī): minggu / hari, 四 (sì): empat
A41: 40 | B41: Angka & waktu | C41: Kapan? | D41: Shénme shíhou? | E41: 什么时候？ | F41: 什么 (shénme): apa, 时候 (shíhou): waktu
A42: 41 | B42: Angka & waktu | C42: Lima | D42: Wǔ | E42: 五 | F42: 五 (wǔ): lima
A43: 42 | B43: Angka & waktu | C43: Lima belas | D43: Shíwǔ | E43: 十五 | F43: 十 (shí): sepuluh, 五 (wǔ): lima
A44: 43 | B44: Angka & waktu | C44: Lusa | D44: Hòutiān | E44: 后天 | F44: 后 (hòu): setelah, 天 (tiān): hari, 后天 (hòutiān): lusa
A45: 44 | B45: Angka & waktu | C45: Maret | D45: Sānyuè | E45: 三月 | F45: 三 (sān): tiga, 月 (yuè): bulan
A46: 45 | B46: Angka & waktu | C46: Mei | D46: Wǔyuè | E46: 五月 | F46: 五 (wǔ): lima, 月 (yuè): bulan
A47: 46 | B47: Angka & waktu | C47: Minggu | D47: Xīngqīrì / xīngqītiān | E47: 星期日 / 星期天 | F47: 星期 (xīngqī): minggu / hari, 日 (rì) / 天 (tiān): hari / matahari | G47: Bisa juga 周日 (zhōurì), 周 = singkatan 星期
A48: 47 | B48: Angka & waktu | C48: Minggu depan | D48: Xià ge xīngqī | E48: 下个星期 | F48: 下 (xià): berikutnya, 个 (gè): kata penggolong, 星期 (xīngqī): minggu
A49: 48 | B49: Angka & waktu | C49: November | D49: Shíyīyuè | E49: 十一月 | F49: 十一 (shíyī): sebelas, 月 (yuè): bulan
A50: 49 | B50: Angka & waktu | C50: Oktober | D50: Shíyuè | E50: 十月 | F50: 十 (shí): sepuluh, 月 (yuè): bulan
A51: 50 | B51: Angka & waktu | C51: Rabu | D51: Xīngqīsān | E51: 星期三 | F51: 星期 (xīngqī): minggu / hari, 三 (sān): tiga
A52: 51 | B52: Angka & waktu | C52: Sabtu | D52: Xīngqīliù | E52: 星期六 | F52: 星期 (xīngqī): minggu / hari, 六 (liù): enam
A53: 52 | B53: Angka & waktu | C53: Satu | D53: Yī | E53: 一 | F53: 一 (yī): satu
A54: 53 | B54: Angka & waktu | C54: Sebelas | D54: Shíyī | E54: 十一 | F54: 十 (shí): sepuluh, 一 (yī): satu
A55: 54 | B55: Angka & waktu | C55: Sedikit | D55: Yìdiǎn | E55: 一点 | F55: 一点 (yìdiǎn): sedikit
A56: 55 | B56: Angka & waktu | C56: Sekarang | D56: Xiànzài | E56: 现在 | F56: 现 (xiàn): kini, 在 (zài): berada, 现在 (xiànzài): sekarang
A57: 56 | B57: Angka & waktu | C57: Selasa | D57: Xīngqī'èr | E57: 星期二 | F57: 星期 (xīngqī): minggu / hari, 二 (èr): dua
A58: 57 | B58: Angka & waktu | C58: Sembilan | D58: Jiǔ | E58: 九 | F58: 九 (jiǔ): sembilan
A59: 58 | B59: Angka & waktu | C59: Senin | D59: Xīngqīyī | E59: 星期一 | F59: 星期 (xīngqī): minggu / hari, 一 (yī): satu
... A63: 62 | B63: Angka & waktu | C63: Tahun depan | D63: Míngnián | E63: 明年 | F63: 明 (míng): berikutnya, 年 (nián): tahun
A64: 63 | B64: Angka & waktu | C64: Tahun dua ribu dua puluh enam | D64: Èr líng èr liù nián | E64: 二零二六年 | F64: 二 (èr): dua, 零 (líng): nol, 二 (èr): dua, 六 (liù): enam, 年 (nián): tahun | G64: Tahun dibaca per angka
A65: 64 | B65: Angka & waktu | C65: Tahun ini | D65: Jīnnián | E65: 今年 | F65: 今 (jīn): ini, 年 (nián): tahun
A66: 65 | B66: Angka & waktu | C66: Tahun lalu | D66: Qùnián | E66: 去年 | F66: 去 (qù): lalu, 年 (nián): tahun
A67: 66 | B67: Angka & waktu | C67: Tiga | D67: Sān | E67: 三 | F67: 三 (sān): tiga
A68: 67 | B68: Angka & waktu | C68: Tiga belas | D68: Shísān | E68: 十三 | F68: 十 (shí): sepuluh, 三 (sān): tiga
A69: 68 | B69: Angka & waktu | C69: Tujuh | D69: Qī | E69: 七 | F69: 七 (qī): tujuh
A70: 69 | B70: Angka & waktu | C70: Enam belas (16) | D70: Shíliù | E70: 十六 | F70: 十 (shí): sepuluh, 六 (liù): enam
A71: 70 | B71: Angka & waktu | C71: Tujuh belas (17) | D71: Shíqī | E71: 十七 | F71: 十 (shí): sepuluh, 七 (qī): tujuh
A72: 71 | B72: Angka & waktu | C72: Delapan belas (18) | D72: Shíbā | E72: 十八 | F72: 十 (shí): sepuluh, 八 (bā): delapan
A73: 72 | B73: Angka & waktu | C73: Sembilan belas (19) | D73: Shíjiǔ | E73: 十九 | F73: 十 (shí): sepuluh, 九 (jiǔ): sembilan
A74: 73 | B74: Angka & waktu | C74: Tiga puluh (30) | D74: Sānshí | E74: 三十 | F74: 三 (sān): tiga, 十 (shí): sepuluh
A75: 74 | B75: Angka & waktu | C75: Empat puluh (40) | D75: Sìshí | E75: 四十 | F75: 四 (sì): empat, 十 (shí): sepuluh
A76: 75 | B76: Angka & waktu | C76: Lima puluh (50) | D76: Wǔshí | E76: 五十 | F76: 五 (wǔ): lima, 十 (shí): sepuluh
... A94: 93 | B94: Angka & waktu | C94: Lima puluh ribu (50.000) | D94: Wǔwàn | E94: 五万 | F94: 五 (wǔ): lima, 万 (wàn): sepuluh ribu
A95: 94 | B95: Angka & waktu | C95: Seratus ribu (100.000) | D95: Shíwàn | E95: 十万 | F95: 十 (shí): sepuluh, 万 (wàn): sepuluh ribu | G95: Mandarin pakai 万 (sepuluh ribu), bukan 百千
A96: 95 | B96: Angka & waktu | C96: Dua ratus ribu (200.000) | D96: Èrshíwàn | E96: 二十万 | F96: 二十 (èrshí): dua puluh, 万 (wàn): sepuluh ribu
A97: 96 | B97: Angka & waktu | C97: Lima ratus ribu (500.000) | D97: Wǔshíwàn | E97: 五十万 | F97: 五十 (wǔshí): lima puluh, 万 (wàn): sepuluh ribu
A98: 97 | B98: Angka & waktu | C98: Sembilan ratus ribu (900.000) | D98: Jiǔshíwàn | E98: 九十万 | F98: 九十 (jiǔshí): sembilan puluh, 万 (wàn): sepuluh ribu
A99: 98 | B99: Belanja & pembayaran | C99: Berapa totalnya? | D99: Yígòng duōshao qián? | E99: 一共多少钱？ | F99: 一共 (yígòng): total / seluruhnya, 多少 (duōshao): berapa, 钱 (qián): uang / harga | H99: Belum
A100: 99 | B100: Belanja & pembayaran | C100: Terlalu mahal | D100: Tài guì le | E100: 太贵了 | F100: 太 (tài): terlalu, 贵 (guì): mahal, 了 (le): partikel penegas | H100: Belum
A101: 100 | B101: Belanja & pembayaran | C101: Bisa lebih murah? | D101: Kěyǐ piányi yìdiǎnr ma? | E101: 可以便宜一点儿吗？ | F101: 可以 (kěyǐ): bisa, 便宜 (piányi): murah, 一点儿 (yìdiǎnr): sedikit, 吗 (ma): partikel tanya | H101: Belum
A102: 101 | B102: Belanja & pembayaran | C102: Saya beli ini | D102: Wǒ mǎi zhège | E102: 我买这个 | F102: 我 (wǒ): saya, 买 (mǎi): beli, 这个 (zhège): ini | H102: Belum
A103: 102 | B103: Belanja & pembayaran | C103: Saya hanya melihat-lihat | D103: Wǒ suíbiàn kànkan | E103: 我随便看看 | F103: 我 (wǒ): saya, 随便 (suíbiàn): santai / tanpa tujuan, 看看 (kànkan): lihat-lihat | H103: Belum
A104: 103 | B104: Belanja & pembayaran | C104: Boleh saya coba? | D104: Kěyǐ shì yíxià ma? | E104: 可以试一下吗？ | F104: 可以 (kěyǐ): boleh, 试 (shì): coba, 一下 (yíxià): sekali, 吗 (ma): partikel tanya | H104: Belum
A105: 104 | B105: Belanja & pembayaran | C105: Apakah ada ukuran lain? | D105: Yǒu bié de chǐmǎ ma? | E105: 有别的尺码吗？ | F105: 有 (yǒu): ada, 别的 (bié de): yang lain, 尺码 (chǐmǎ): ukuran, 吗 (ma): partikel tanya | H105: Belum
A106: 105 | B106: Belanja & pembayaran | C106: Bisa bayar pakai WeChat Pay? | D106: Kěyǐ yòng Wēixìn zhīfù ma? | E106: 可以用微信支付吗？ | F106: 可以 (kěyǐ): bisa, 用 (yòng): pakai, 微信 (Wēixìn): WeChat, 支付 (zhīfù): pembayaran, 吗 (ma): partikel tanya | H106: Belum
A107: 106 | B107: Belanja & pembayaran | C107: Bisa bayar pakai Alipay? | D107: Kěyǐ yòng zhīfùbǎo ma? | E107: 可以用支付宝吗？ | F107: 可以 (kěyǐ): bisa, 用 (yòng): pakai, 支付宝 (zhīfùbǎo): Alipay, 吗 (ma): partikel tanya | H107: Belum
A108: 107 | B108: Belanja & pembayaran | C108: Bisa pakai kartu? | D108: Kěyǐ shuā kǎ ma? | E108: 可以刷卡吗？ | F108: 可以 (kěyǐ): bisa, 刷卡 (shuā kǎ): gesek kartu, 吗 (ma): partikel tanya | H108: Belum
A109: 108 | B109: Belanja & pembayaran | C109: Saya bayar tunai | D109: Wǒ fù xiànjīn | E109: 我付现金 | F109: 我 (wǒ): saya, 付 (fù): bayar, 现金 (xiànjīn): uang tunai | G109: Banyak tempat tidak menerima tunai | H109: Belum
A110: 109 | B110: Belanja & pembayaran | C110: Di mana ada minimarket? | D110: Nǎlǐ yǒu biànlìdiàn? | E110: 哪里有便利店？ | F110: 哪里 (nǎlǐ): di mana, 有 (yǒu): ada, 便利店 (biànlìdiàn): minimarket | H110: Belum
A111: 110 | B111: Belanja & pembayaran | C111: Di mana ada apotek? | D111: Nǎlǐ yǒu yàodiàn? | E111: 哪里有药店？ | F111: 哪里 (nǎlǐ): di mana, 有 (yǒu): ada, 药店 (yàodiàn): apotek | H111: Belum
A112: 111 | B112: Belanja & pembayaran | C112: Di mana tempat tukar uang? | D112: Nǎlǐ kěyǐ huàn qián? | E112: 哪里可以换钱？ | F112: 哪里 (nǎlǐ): di mana, 可以 (kěyǐ): bisa, 换 (huàn): tukar, 钱 (qián): uang | H112: Belum
A113: 112 | B113: Belanja & pembayaran | C113: Saya mau beli kartu SIM | D113: Wǒ xiǎng mǎi yì zhāng shǒujī kǎ | E113: 我想买一张手机卡 | F113: 我 (wǒ): saya, 想 (xiǎng): ingin, 买 (mǎi): beli, 一 (yì): satu, 张 (zhāng): kata penggolong benda tipis/kartu, 手机卡 (shǒujī kǎ): kartu SIM | G113: Biasanya butuh paspor | H113: Belum
A114: 113 | B114: Belanja & pembayaran | C114: Apa password Wi-Fi? | D114: Wi-Fi mìmǎ shì duōshao? | E114: Wi-Fi密码是多少？ | F114: Wi-Fi (Wi-Fi): Wi-Fi, 密码 (mìmǎ): password, 是 (shì): adalah, 多少 (duōshao): berapa / apa | H114: Belum
A115: 114 | B115: Belanja & pembayaran | C115: Banyak | D115: Duō | E115: 多 | F115: 多 (duō): banyak
A116: 115 | B116: Belanja & pembayaran | C116: Baru | D116: Xīn | E116: 新 | F116: 新 (xīn): baru
A117: 116 | B117: Belanja & pembayaran | C117: Bekas | D117: Èrshǒu | E117: 二手 | F117: 二手 (èrshǒu): barang bekas / second-hand
A118: 117 | B118: Belanja & pembayaran | C118: Besar | D118: Dà | E118: 大 | F118: 大 (dà): besar
A119: 118 | B119: Belanja & pembayaran | C119: Ini berapa? (menanyakan harga) | D119: Zhè duōshao qián? | E119: 这多少钱？ | F119: 这 (zhè): ini, 多少 (duōshao): berapa, 钱 (qián): harga / uang
A120: 119 | B120: Belanja & pembayaran | C120: Ini saja? | D120: Jiù zhè ge ma? | E120: 就这个吗？ | F120: 就 (jiù): hanya, 这个 (zhè ge): ini, 吗 (ma): partikel tanya
...

Sheet Progress
A1: Progress hafalan
A2: Ubah kolom Status di sheet "Survival 200" (Belum / Sedang / Hafal). Tabel otomatis terhitung untuk seluruh kalimat.
A4: Situasi | B4: Total kalimat | C4: Hafal | D4: Sedang | E4: % Hafal
A5: Salam & sopan santun | B5: =COUNTIFS('Survival 200'!$B$2:$B$1000,A5) | C5: =COUNTIFS('Survival 200'!$B$2:$B$1000,A5,'Survival 200'!$H$2:$H$1000,"Hafal") | D5: =COUNTIFS('Survival 200'!$B$2:$B$1000,A5,'Survival 200'!$H$2:$H$1000,"Sedang") | E5: =IF(B5=0,0,C5/B5)
A6: Perkenalan | B6: =COUNTIFS('Survival 200'!$B$2:$B$1000,A6) | C6: =COUNTIFS('Survival 200'!$B$2:$B$1000,A6,'Survival 200'!$H$2:$H$1000,"Hafal") | D6: =COUNTIFS('Survival 200'!$B$2:$B$1000,A6,'Survival 200'!$H$2:$H$1000,"Sedang") | E6: =IF(B6=0,0,C6/B6)
A7: Tidak mengerti & minta bantuan | B7: =COUNTIFS('Survival 200'!$B$2:$B$1000,A7) | C7: =COUNTIFS('Survival 200'!$B$2:$B$1000,A7,'Survival 200'!$H$2:$H$1000,"Hafal") | D7: =COUNTIFS('Survival 200'!$B$2:$B$1000,A7,'Survival 200'!$H$2:$H$1000,"Sedang") | E7: =IF(B7=0,0,C7/B7)
A8: Ya, tidak, boleh | B8: =COUNTIFS('Survival 200'!$B$2:$B$1000,A8) | C8: =COUNTIFS('Survival 200'!$B$2:$B$1000,A8,'Survival 200'!$H$2:$H$1000,"Hafal") | D8: =COUNTIFS('Survival 200'!$B$2:$B$1000,A8,'Survival 200'!$H$2:$H$1000,"Sedang") | E8: =IF(B8=0,0,C8/B8)
A9: Angka & waktu | B9: =COUNTIFS('Survival 200'!$B$2:$B$1000,A9) | C9: =COUNTIFS('Survival 200'!$B$2:$B$1000,A9,'Survival 200'!$H$2:$H$1000,"Hafal") | D9: =COUNTIFS('Survival 200'!$B$2:$B$1000,A9,'Survival 200'!$H$2:$H$1000,"Sedang") | E9: =IF(B9=0,0,C9/B9)
A10: Makan & minum | B10: =COUNTIFS('Survival 200'!$B$2:$B$1000,A10) | C10: =COUNTIFS('Survival 200'!$B$2:$B$1000,A10,'Survival 200'!$H$2:$H$1000,"Hafal") | D10: =COUNTIFS('Survival 200'!$B$2:$B$1000,A10,'Survival 200'!$H$2:$H$1000,"Sedang") | E10: =IF(B10=0,0,C10/B10)
A11: Belanja & pembayaran | B11: =COUNTIFS('Survival 200'!$B$2:$B$1000,A11) | C11: =COUNTIFS('Survival 200'!$B$2:$B$1000,A11,'Survival 200'!$H$2:$H$1000,"Hafal") | D11: =COUNTIFS('Survival 200'!$B$2:$B$1000,A11,'Survival 200'!$H$2:$H$1000,"Sedang") | E11: =IF(B11=0,0,C11/B11)
A12: Transportasi & arah | B12: =COUNTIFS('Survival 200'!$B$2:$B$1000,A12) | C12: =COUNTIFS('Survival 200'!$B$2:$B$1000,A12,'Survival 200'!$H$2:$H$1000,"Hafal") | D12: =COUNTIFS('Survival 200'!$B$2:$B$1000,A12,'Survival 200'!$H$2:$H$1000,"Sedang") | E12: =IF(B12=0,0,C12/B12)
A13: Hotel | B13: =COUNTIFS('Survival 200'!$B$2:$B$1000,A13) | C13: =COUNTIFS('Survival 200'!$B$2:$B$1000,A13,'Survival 200'!$H$2:$H$1000,"Hafal") | D13: =COUNTIFS('Survival 200'!$B$2:$B$1000,A13,'Survival 200'!$H$2:$H$1000,"Sedang") | E13: =IF(B13=0,0,C13/B13)
A14: Pelatihan & kerja | B14: =COUNTIFS('Survival 200'!$B$2:$B$1000,A14) | C14: =COUNTIFS('Survival 200'!$B$2:$B$1000,A14,'Survival 200'!$H$2:$H$1000,"Hafal") | D14: =COUNTIFS('Survival 200'!$B$2:$B$1000,A14,'Survival 200'!$H$2:$H$1000,"Sedang") | E14: =IF(B14=0,0,C14/B14)
A15: Kesehatan | B15: =COUNTIFS('Survival 200'!$B$2:$B$1000,A15) | C15: =COUNTIFS('Survival 200'!$B$2:$B$1000,A15,'Survival 200'!$H$2:$H$1000,"Hafal") | D15: =COUNTIFS('Survival 200'!$B$2:$B$1000,A15,'Survival 200'!$H$2:$H$1000,"Sedang") | E15: =IF(B15=0,0,C15/B15)
A16: Darurat | B16: =COUNTIFS('Survival 200'!$B$2:$B$1000,A16) | C16: =COUNTIFS('Survival 200'!$B$2:$B$1000,A16,'Survival 200'!$H$2:$H$1000,"Hafal") | D16: =COUNTIFS('Survival 200'!$B$2:$B$1000,A16,'Survival 200'!$H$2:$H$1000,"Sedang") | E16: =IF(B16=0,0,C16/B16)
A17: Sosial & penutup | B17: =COUNTIFS('Survival 200'!$B$2:$B$1000,A17) | C17: =COUNTIFS('Survival 200'!$B$2:$B$1000,A17,'Survival 200'!$H$2:$H$1000,"Hafal") | D17: =COUNTIFS('Survival 200'!$B$2:$B$1000,A17,'Survival 200'!$H$2:$H$1000,"Sedang") | E17: =IF(B17=0,0,C17/B17)
A18: Total | B18: =SUM(B5:B17) | C18: =SUM(C5:C17) | D18: =SUM(D5:D17) | E18: =IF(B18=0,0,C18/B18)
A20: Legenda warna duplikat (sheet Survival 200)
A21: C - Indonesia sama, Hanzi beda

Sheet Kamus
A1: No. | B1: Kalimat dalam bahasa Indonesia | C1: arti kalimat atau kata dalam pinyin | D1: arti kalimat atau kata dalam hanzi | E1: arti perkata dalam Bahasa Indonesia | F1: Keterangan | G1: label | H1: Contoh 1 - Indonesia | I1: Contoh 1 - Pinyin | J1: Contoh 1 - Hanzi | K1: Contoh 2 - Indonesia | L1: Contoh 2 - Pinyin | M1: Contoh 2 - Hanzi | N1: Contoh 3 - Indonesia | O1: Contoh 3 - Pinyin | P1: Contoh 3 - Hanzi
A2: 1 | B2: "apakah oke?" atau "apakah bisa?" | C2: Xíng ma? | D2: 行吗？ | E2: 行 (xíng): oke / bisa, 吗 (ma): partikel tanya | G2: Umum: sering dipakai native dalam percakapan sehari-hari. | H2: Kita makan siang jam dua, oke? | I2: Wǒmen liǎng diǎn chī wǔfàn, xíng ma? | J2: 我们两点吃午饭，行吗？ | K2: Kamu pulang dulu, besok saja, oke? | L2: Nǐ xiān huí qù, míngtiān zài shuō, xíng ma? | M2: 你先回去，明天再说，行吗？ | N2: Laporan ini bisa selesai besok, apakah oke? | O2: Zhè fèn bàogào míngtiān néng wán, xíng ma? | P2: 这份报告明天能完成，行吗？
A3: 2 | B3: "Hampir sama" atau "Kurang lebih sama" | C3: Chàbuduō | D3: 差不多 | E3: 差不多 (chàbuduō): hampir sama; 差 (chà): kurang, 不多 (bùduō): tidak banyak | G3: Umum: sering dipakai native dalam percakapan sehari-hari. | H3: Dua produk ini hampir sama. | I3: Zhè liǎng ge chǎnpǐn chàbuduō. | J3: 这两个产品差不多。 | K3: Hasil tes kami hampir sama. | L3: Wǒmen de cèshì jiéguǒ chàbuduō. | M3: 我们的测试结果差不多。 | N3: Harganya hampir sama dengan kemarin. | O3: Jiàgé hé zuótiān chàbuduō. | P3: 价格和昨天差不多。
A4: 3 | B4: 2 Orang | C4: liǎng gè rén | D4: 两个人 | E4: 两 (liǎng): dua, 个 (gè): kata penggolong, 人 (rén): orang | F4: Sebelum kata penggolong pakai 两, bukan 二 | G4: Umum: sering dipakai native dalam percakapan sehari-hari. | H4: Ada dua orang di ruang QC. | I4: Zhìjiǎn shì yǒu liǎng gè rén. | J4: 质检室有两个人。 | K4: Kami butuh dua orang untuk shift malam. | L4: Yè bān xūyào liǎng gè rén. | M4: 夜班需要两个人。 | N4: Tolong siapkan meja untuk dua orang. | O4: Qǐng zhǔnbèi liǎng gè rén de zhuōzi. | P4: 请准备两个人的桌子。
A5: 4 | B5: 3D Test/Pengujian 3D | C5: 3D cèshì | D5: 3D测试 | E5: 3D (sān D): tiga dimensi, 测试 (cèshì): pengujian | F5: Dibaca "sān D cèshì" | G5: Umum di pabrik: Dibaca "sān D cèshì"; dipakai di komunikasi kerja. | H5: Mesin 3D test sedang dipakai. | I5: 3D cèshì jī zhèng zài yòng. | J5: 3D测试机正在用。 | K5: Hasil 3D test sudah keluar. | L5: 3D cèshì de jiéguǒ chūlái le. | M5: 3D测试的结果出来了。 | N5: Setelah optic test, lanjut 3D test. | O5: Guāngxué cèshì yǐhòu, jìxù 3D cèshì. | P5: 光学测试以后，继续3D测试。
A6: 5 | B6: ada | C6: yǒu | D6: 有 | E6: 有 (yǒu): ada / punya | G6: Umum: sering dipakai native dalam percakapan sehari-hari. | H6: Di sini ada kursi kosong. | I6: Zhèr yǒu kòng yǐzi. | J6: 这儿有空椅子。 | K6: Saya ada waktu sore ini. | L6: Wǒ jīntiān xiàwǔ yǒu shíjiān. | M6: 我今天下午有时间。 | N6: Ada masalah di mesin nomor dua. | O6: Èr hào jī yǒu wèntí. | P6: 二号机有问题。
A7: 6 | B7: ada apa? | C7: yǒu shénme shì? | D7: 有什么事？ | E7: 有 (yǒu): ada, 什么 (shénme): apa, 事 (shì): urusan / masalah | G7: Umum: sering dipakai native dalam percakapan sehari-hari. | H7: Ada apa? Kenapa kamu terlihat sedih? | I7: Yǒu shénme shì? Nǐ zěnme kànqǐlái hěn nánguò? | J7: 有什么事？你怎么看起来很难过？ | K7: Ada apa di sana? | L7: Nàbiān yǒu shénme shì? | M7: 那边有什么事？ | N7: Ada apa, kok ramai sekali? | O7: Yǒu shénme shì, zěnme zhème rènao? | P7: 有什么事，怎么这么热闹？
A8: 7 | B8: ada tidak? | C8: yǒu méiyǒu? | D8: 有没有？ | E8: 有 (yǒu): ada, 没有 (méiyǒu): tidak ada | G8: Umum: sering dipakai native dalam percakapan sehari-hari. | H8: Ada tidak kertas? | I8: Yǒu méiyǒu zhǐ? | J8: 有没有纸？ | K8: Ada tidak yang lebih murah? | L8: Yǒu méiyǒu piányi yìdiǎn de? | M8: 有没有便宜一点的？ | N8: Laporan yang kemarin ada tidak? | O8: Zuótiān de bàogào yǒu méiyǒu? | P8: 昨天的报告有没有？
A9: 8 | B9: ada tidak? | C9: yǒu méiyǒu? | D9: 有没有 | E9: 有 (yǒu): ada, 没有 (méiyǒu): tidak ada | G9: Umum: sering dipakai native dalam percakapan sehari-hari. | H9: Ada tidak orang yang bisa bantu? | I9: Yǒu méiyǒu rén néng bāng máng? | J9: 有没有人能帮忙？ | K9: Ada tidak data bulan Agustus? | L9: Yǒu méiyǒu bāyuè de shùjù? | M9: 有没有八月的数据？ | N9: Ada tidak tempat parkir di sini? | O9: Zhèr yǒu méiyǒu tíngchē de dìfang? | P9: 这儿有没有停车的地方？
A10: 9 | B10: ada? | C10: yǒu ma? | D10: 有吗？ | E10: 有 (yǒu): ada, 吗 (ma): partikel tanya | G10: Umum: sering dipakai native dalam percakapan sehari-hari. | H10: Ada? Saya tidak dengar. | I10: Yǒu ma? Wǒ méi tīngjiàn. | J10: 有吗？我没听见。 | K10: Masih ada stok, ada? | L10: Hái yǒu huòcún ma? | M10: 还有库存吗？ | N10: Ada orang di dalam? | O10: Lǐmiàn yǒu rén ma? | P10: 里面有人吗？
A11: 10 | B11: Agustus | C11: bāyuè | D11: 八月 | E11: 八 (bā): delapan, 月 (yuè): bulan | G11: Umum: sering dipakai native dalam percakapan sehari-hari. | H11: Produksi bulan Agustus naik. | I11: Bāyuè de chǎnliàng shàngshēng le. | J11: 八月的产量上升了。 | K11: Laporan Agustus sudah dikirim. | L11: Bāyuè de bàogào yǐjīng fā chūqù le. | M11: 八月的报告已经发出去了。 | N11: Kami mulai shift baru pada Agustus. | O11: Wǒmen bāyuè kāishǐ xīn de bān. | P11: 我们八月开始新的班。
A12: 11 | B12: apakah boleh? | C12: Kěyǐ ma? | D12: 可以吗？ | E12: Kěyǐ berarti "boleh" atau "bisa", dan ma adalah partikel tanya di akhir kalimat. | G12: Umum: sering dipakai native dalam percakapan sehari-hari. | H12: Saya pulang lebih awal, apakah boleh? | I12: Wǒ zǎo diǎn huí qù, kěyǐ ma? | J12: 我早点回去，可以吗？ | K12: Boleh saya pinjam pena? | L12: Wǒ kěyǐ jiè yì zhī bǐ ma? | M12: 我可以借一支笔吗？ | N12: Apakah boleh foto di area produksi? | O12: Shēngchǎn qūyù kěyǐ pāizhào ma? | P12: 生产区域可以拍照吗？
A13: 12 | B13: Apakah cara mengerjakannya seperti ini sudah benar? | C13: Zhèyàng zuò duì ma? | D13: 这样做对吗？ | E13: Zhèyàng (这样) = Begini / seperti ini, Zuò (做) = Mengerjakan / membuat, Duì (对) = Benar, Ma (吗) = Partikel tanya di akhir kalimat | G13: Kurang umum: Kalimat panjang; native biasanya cukup 这样做对吗？ | H13: Saya isi kolom dengan cara ini, apakah sudah benar? | I13: Wǒ zhèyàng tián lán, zhèyàng zuò duì ma? | J13: 我这样填栏，这样做对吗？ | K13: Saya cuci komponen dengan cara ini, sudah benar? | L13: Wǒ zhèyàng xǐ língjiàn, zhèyàng zuò duì ma? | M13: 我这样洗零件，这样做对吗？ | N13: Cara kalibrasi seperti ini sudah benar? | O13: Zhèyàng jiàozhǔn zuò duì ma? | P13: 这样校准做对吗？
A14: 13 | B14: Apakah ini benar? | C14: zhèyàng duì ma? | D14: 这样对吗？ | E14: 这样 (zhèyàng): seperti ini, 对 (duì): benar, 吗 (ma): partikel tanya | G14: Umum: sering dipakai native dalam percakapan sehari-hari. | H14: Apakah ini benar? Saya sudah cek dua kali. | I14: Zhèyàng duì ma? Wǒ jiǎnchále liǎng cì. | J14: 这样对吗？我检查了两次。 | K14: Apakah ini benar? Tolong cek lagi. | L14: Zhèyàng duì ma? Qǐng zài jiǎnchá yíxià. | M14: 这样对吗？请再检查一下。 | N14: Apakah ini benar, sesuai SOP? | O14: Zhèyàng duì ma, fúhé SOP ma? | P14: 这样对吗，符合SOP吗？
A15: 14 | B15: Apakah masih ada? | C15: Hái yǒu ma? | D15: 还有吗? | E15: hái (还) berarti "masih", dan yǒu (有) berarti "ada". | G15: Umum: sering dipakai native dalam percakapan sehari-hari. | H15: Masih ada stok kertas? | I15: Hái yǒu zhǐ de kùcún ma? | J15: 还有纸的库存吗？ | K15: Masih ada waktu sebelum rapat. | L15: Kāihuì qián hái yǒu shíjiān. | M15: 开会前还有时间。 | N15: Masih ada beberapa barang yang belum dikirim. | O15: Hái yǒu yìxiē dōngxi méi fāchū. | P15: 还有一些东西没发出。
A16: 15 | B16: apakah seperti ini? | C16: shì zhèyàng ma? | D16: 是这样吗？ | E16: 是 (shì): adalah, 这样 (zhèyàng): seperti ini, 吗 (ma): partikel tanya | G16: Umum: sering dipakai native dalam percakapan sehari-hari. | H16: Apakah seperti ini? Saya tekan tombol merah. | I16: Shì zhèyàng ma? Wǒ àn le hóngsè de ànniǔ. | J16: 是这样吗？我按了红色的按钮。 | K16: Jadi maksudmu seperti ini? | L16: Suǒyǐ nǐ de yìsi shì zhèyàng ma? | M16: 所以你的意思是这样吗？ | N16: Apakah seperti ini saat alarm berbunyi? | O16: Bàojǐng xiǎng de shíhou shì zhèyàng ma? | P16: 报警响的时候是这样吗？
A17: 16 | B17: Apakah yang ini? | C17: shì zhè ge ma? | D17: 是这个吗？ | E17: 是 (shì): adalah, 这个 (zhè ge): yang ini, 吗 (ma): partikel tanya | G17: Umum: sering dipakai native dalam percakapan sehari-hari. | H17: Apakah yang ini? Yang biru itu? | I17: Shì zhè ge ma? Shì nà ge lánsè de ma? | J17: 是这个吗？是那个蓝色的吗？ | K17: Apakah yang ini barang yang rusak? | L17: Shì zhè ge huài le de dōngxi ma? | M17: 是这个坏了的东西吗？ | N17: Apakah yang ini sudah diperiksa? | O17: Shì zhè ge yǐjīng jiǎnchá guò le ma? | P17: 是这个已经检查过了吗？
... A32: 31 | B32: benar / iya benar | C32: duì de | D32: 对的 | E32: 对 (duì): benar, 的 (de): partikel penegas, 对的 (duì de): benar / iya | G32: Umum: sering dipakai native dalam percakapan sehari-hari. | H32: Iya benar, begitu caranya. | I32: Duì de, jiù shì zhèyàng. | J32: 对的，就是这样。 | K32: Benar, angkanya sudah sesuai. | L32: Duì de, shùzì duì le. | M32: 对的，数字对了。 | N32: Iya benar, kamu tidak salah. | O32: Duì de, nǐ méi cuò. | P32: 对的，你没错。
A33: 32 | B33: berapa harganya? | C33: duōshao qián? | D33: 多少钱？ | E33: 多少 (duōshao): berapa, 钱 (qián): uang / harga | F33: Pinyin dikoreksi dari "duìshǎo qián" | G33: Umum: sering dipakai native dalam percakapan sehari-hari. | H33: Berapa harganya? | I33: Duōshao qián? | J33: 多少钱？ | K33: Berapa harganya untuk 10 pcs? | L33: Shí ge duōshao qián? | M33: 十个多少钱？ | N33: Tolong beritahu saya berapa harganya. | O33: Qǐng gàosu wǒ duōshao qián. | P33: 请告诉我多少钱。
A34: 33 | B34: Besar | C34: dà | D34: 大 | E34: 大 (dà): besar | G34: Umum: sering dipakai native dalam percakapan sehari-hari. | H34: Ukuran kotaknya besar. | I34: Hézi de chǐcun hěn dà. | J34: 盒子的尺寸很大。 | K34: Ini mesin yang besar. | L34: Zhè shì yí tái hěn dà de jī. | M34: 这是一台很大的机。 | N34: Ruangan ini besar sekali. | O34: Zhè ge fángjiān hěn dà. | P34: 这个房间很大。
A35: 34 | B35: Besok | C35: míngtiān | D35: 明天 | E35: 明 (míng): esok, 天 (tiān): hari, 明天 (míngtiān): besok | G35: Umum: sering dipakai native dalam percakapan sehari-hari. | H35: Besok kita rapat jam sembilan. | I35: Míngtiān wǒmen jiǔ diǎn kāi huì. | J35: 明天我们九点开会。 | K35: Besok saya cuti. | L35: Míngtiān wǒ xiūjià. | M35: 明天我休假。 | N35: Kirim laporannya besok pagi. | O35: Míngtiān zǎoshang bǎ bàogào fā guòlái. | P35: 明天早上把报告发过来。
A36: 35 | B36: bisa | C36: huì / néng | D36: 会 / 能 | E36: 会 (huì): bisa (karena keahlian/pembelajaran), 能 (néng): bisa (karena kemampuan/kondisi) | G36: Umum: sering dipakai native dalam percakapan sehari-hari. | H36: Saya bisa berbahasa Mandarin sedikit. | I36: Wǒ huì shuō yìdiǎn Zhōngwén. | J36: 我会说一点中文。 | K36: Mesin ini bisa dipakai besok. | L36: Zhè tái jī míngtiān néng yòng. | M36: 这台机明天能用。 | N36: Kamu bisa datang jam berapa? | O36: Nǐ jǐ diǎn néng lái? | P36: 你几点能来？
A37: 36 | B37: bisakah kamu ulangi? | C37: nǐ néng zài shuō yí biàn ma? | D37: 你能再说一遍吗？ | E37: 你 (nǐ): kamu, 能 (néng): bisa, 再 (zài): lagi, 说 (shuō): berbicara, 一遍 (yí biàn): sekali, 吗 (ma): partikel tanya | F37: Diubah ke bentuk tanya agar sesuai kolom B. Bentuk perintah ("tolong ulangi"): lihat baris 142 | G37: Umum: sering dipakai native dalam percakapan sehari-hari. | H37: Maaf, bisakah kamu ulangi? | I37: Duìbuqǐ, nǐ néng zài shuō yí biàn ma? | J37: 对不起，你能再说一遍吗？ | K37: Saya tidak dengar, bisakah kamu ulangi? | L37: Wǒ méi tīng qīngchu, nǐ néng zài shuō yí biàn ma? | M37: 我没听清楚，你能再说一遍吗？ | N37: Bisakah kamu ulangi angka yang tadi? | O37: Nǐ néng zài shuō yí biàn gāngcái de shùzì ma? | P37: 你能再说一遍刚才的数字吗？
A38: 37 | B38: boleh | C38: kěyǐ | D38: 可以 | E38: 可 (kě): dapat, 以 (yǐ): boleh, 可以 (kěyǐ): boleh | G38: Umum: sering dipakai native dalam percakapan sehari-hari. | H38: Di sini boleh merokok? | I38: Zhèr kěyǐ chōuyān ma? | J38: 这儿可以抽烟吗？ | K38: Boleh saya pulang sekarang? | L38: Wǒ xiànzài kěyǐ huí qù ma? | M38: 我现在可以回去吗？ | N38: Di area produksi tidak boleh makan. | O38: Zài shēngchǎn qūyù bù kěyǐ chī dōngxi. | P38: 在生产区域不可以吃东西。
A39: 38 | B39: buka | C39: dǎkāi | D39: 打开 | E39: 打 (dǎ): melakukan, 开 (kāi): buka, 打开 (dǎkāi): membuka | F39: Untuk membuka benda/file/pintu | G39: Umum: sering dipakai native dalam percakapan sehari-hari. | H39: Tolong buka pintu itu. | I39: Qǐng dǎkāi nà ge mén. | J39: 请打开那个门。 | K39: Saya buka file laporan. | L39: Wǒ dǎkāi le bàogào wénjiàn. | M39: 我打开了报告文件。 | N39: Buka mesinnya, sekarang. | O39: Xiànzài dǎkāi jī qì. | P39: 现在打开机器。
A40: 39 | B40: bukan | C40: bú shì | D40: 不是 | E40: 不 (bú): tidak, 是 (shì): adalah | G40: Umum: Umum dalam percakapan. | H40: Ini bukan punya saya. | I40: Zhè bú shì wǒ de. | J40: 这不是我的。 | K40: Dia bukan operator, dia supervisor. | L40: Tā bú shì cāozuòyuán, tā shì zhǔguǎn. | M40: 他不是操作员，他是主管。 | N40: Bukan begitu caranya. | O40: Bú shì zhèyàng zuò de. | P40: 不是这样做的。
A41: 40 | B41: bulan depan | C41: xià ge yuè | D41: 下个月 | E41: 下 (xià): berikutnya, 个 (gè): kata penggolong, 月 (yuè): bulan | G41: Umum: sering dipakai native dalam percakapan sehari-hari. | H41: Bulan depan kita mulai produksi baru. | I41: Xià ge yuè wǒmen kāishǐ xīn de shēngchǎn. | J41: 下个月我们开始新的生产。 | K41: Saya akan cuti bulan depan. | L41: Xià ge yuè wǒ yào xiūjià. | M41: 下个月我要休假。 | N41: Target bulan depan lebih tinggi. | O41: Xià ge yuè de mùbiāo gèng gāo. | P41: 下个月的目标更高。
A42: 41 | B42: Burn-in Process/Proses Burn-in | C42: lǎohuà | D42: 老化 | E42: 老 (lǎo): tua, 化 (huà): proses menjadi, 老化 (lǎohuà): penuaan / burn-in | F42: Di manufaktur 老化 = aging / burn-in test | G42: Umum di pabrik: 老化 dipakai di industri untuk aging/burn-in. | H42: Proses burn-in dilakukan selama 24 jam. | I42: Lǎohuà gōngxù zài èrshísì xiǎoshí nèi jìnxíng. | J42: 老化工序在二十四小时内进行。 | K42: Hasil burn-in sudah keluar. | L42: Lǎohuà de jiéguǒ chūlái le. | M42: 老化的结果出来了。 | N42: Mesin burn-in sudah penuh. | O42: Lǎohuà jī mǎn le. | P42: 老化机满了。
A43: 42 | B43: Cable Cutting/Pemotongan Kabel | C43: cáixiàn | D43: 裁线 | E43: 裁 (cái): potong, 线 (xiàn): kabel / kawat, 裁线 (cáixiàn): pemotongan kabel | G43: Umum: sering dipakai native dalam percakapan sehari-hari. | H43: Mesin cable cutting sudah dibersihkan. | I43: Cáixiàn jī yǐjīng qīngxǐ le. | J43: 裁线机已经清洗了。 | K43: Panjang kabel harus benar saat cable cutting. | L43: Cáixiàn shí xiànchǎng yào zhèngquè. | M43: 裁线时线长要正确。 | N43: Operator cable cutting ada di shift pagi. | O43: Cáixiàn cāozuòyuán zài zǎo bān. | P43: 裁线操作员在早班。
A44: 43 | B44: Core Test/Pengujian Core | C44: cèshì | D44: 测试 | E44: 测 (cè): ukur, 试 (shì): uji, 测试 (cèshì): pengujian | G44: Umum di pabrik: 测试 bersifat umum; native biasanya menyebut nama proses yang spesifik. | H44: Core test harus dilakukan sebelum packaging. | I44: Cèshì yào zài bāozhuāng zhīqián jìnxíng. | J44: 测试要在包装之前进行。 | K44: Hasil core test sudah keluar. | L44: Cèshì jiéguǒ chūlái le. | M44: 测试结果出来了。 | N44: Mesin core test sedang rusak. | O44: Cèshì jī huài le. | P44: 测试机坏了。
A45: 44 | B45: Coupling/Penyambungan | C45: ǒuhé | D45: 耦合 | E45: 耦 (ǒu): berpasangan, 合 (hé): menyatu, 耦合 (ǒuhé): coupling / penyambungan | G45: Umum di pabrik: Istilah optik/industri, wajar dipakai di lingkungan kerja. | H45: Proses coupling harus presisi. | I45: Ǒuhé gōngxù yào zhǔnquè. | J45: 耦合工序要准确。 | K45: Hasil coupling dicek setiap jam. | L45: Ǒuhé jiéguǒ měi xiǎoshí jiǎnchá yí cì. | M45: 耦合结果每小时检查一次。 | N45: Coupling loss masih di bawah standar. | O45: Ǒuhé sǔnhào hái zài biāozhǔn yǐxià. | P45: 耦合损耗还在标准以下。
A46: 45 | B46: Curing/Pengerasan Lem | C46: gùhuà | D46: 固化 | E46: 固 (gù): keras / padat, 化 (huà): proses menjadi, 固化 (gùhuà): curing / pengerasan | G46: Umum: sering dipakai native dalam percakapan sehari-hari. | H46: Lem perlu waktu curing sepuluh menit. | I46: Jiāo xūyào gùhuà shí fēnzhōng. | J46: 胶需要固化十分钟。 | K46: Setelah curing, produk harus diperiksa. | L46: Gùhuà hòu, chǎnpǐn yào jiǎnchá. | M46: 固化后，产品要检查。 | N46: Mesin curing sedang panas. | O46: Gùhuà jī zhèng zài rè. | P46: 固化机正在热。
A47: 46 | B47: delapan | C47: bā | D47: 八 | E47: 八 (bā): delapan | G47: Umum: sering dipakai native dalam percakapan sehari-hari. | H47: Ada delapan orang di tim. | I47: Tuánduì yǒu bā gè rén. | J47: 团队有八个人。 | K47: Shift ini delapan jam. | L47: Zhè ge bān shì bā xiǎoshí. | M47: 这个班是八小时。 | N47: Nomor mesinnya delapan. | O47: Jī qì de hàomǎ shì bā. | P47: 机器的号码是八。
A48: 47 | B48: Desember | C48: shí'èryuè | D48: 十二月 | E48: 十二 (shí'èr): dua belas, 月 (yuè): bulan | G48: Umum: sering dipakai native dalam percakapan sehari-hari. | H48: Liburan akhir tahun di bulan Desember. | I48: Niánzhōng jiàqī zài shí'èr yuè. | J48: 年终假期在十二月。 | K48: Laporan tahunan dikirim bulan Desember. | L48: Niándù bàogào zài shí'èr yuè fā chū. | M48: 年度报告在十二月发出。 | N48: Kami selesai proyek ini pada Desember. | O48: Wǒmen shí'èr yuè wánchéng le zhè ge xiàngmù. | P48: 我们十二月完成了这个项目。
A49: 48 | B49: Di mana? | C49: zài nǎr? | D49: 在哪儿？ | E49: 在 (zài): di, 哪儿 (nǎr): mana | G49: Umum: sering dipakai native dalam percakapan sehari-hari. | H49: Di mana toilet? | I49: Cèsuǒ zài nǎr? | J49: 厕所在哪儿？ | K49: Dokumennya di mana? | L49: Wénjiàn zài nǎr? | M49: 文件在哪儿？ | N49: Kamu di mana sekarang? | O49: Nǐ xiànzài zài nǎr? | P49: 你现在在哪儿？
A50: 49 | B50: dia | C50: tā | D50: 他 / 她 | E50: 他 (tā): dia (laki-laki), 她 (tā): dia (perempuan) | G50: Umum: sering dipakai native dalam percakapan sehari-hari. | H50: Dia operator baru. | I50: Tā shì xīn cāozuòyuán. | J50: 他是新操作员。 | K50: Dia sudah pulang. | L50: Tā yǐjīng huí qù le. | M50: 她已经回去了。 | N50: Dia sedang rapat sekarang. | O50: Tā xiànzài zài kāi huì. | P50: 他现在在开会。
A51: 50 | B51: dua | C51: èr | D51: 二 | E51: 二 (èr): dua | G51: Umum: sering dipakai native dalam percakapan sehari-hari. | H51: Dua orang sudah datang. | I51: Liǎng ge rén lái le. | J51: 两个人来了。 | K51: Saya punya dua anak. | L51: Wǒ yǒu liǎng ge háizi. | M51: 我有两个孩子。 | N51: Dua tambah dua sama dengan empat. | O51: Èr jiā èr děngyú sì. | P51: 二加二等于四。
A52: 51 | B52: dua belas | C52: shí'èr | D52: 十二 | E52: 十 (shí): sepuluh, 二 (èr): dua | G52: Umum: sering dipakai native dalam percakapan sehari-hari. | H52: Ada dua belas botol di kotak itu. | I52: Nà ge hézi lǐ yǒu shí'èr píng. | J52: 那个盒子里有十二瓶。 | K52: Shift saya mulai jam dua belas. | L52: Wǒ de bān shí'èr diǎn kāishǐ. | M52: 我的班十二点开始。 | N52: Ada dua belas item yang belum dicek. | O52: Hái yǒu shí'èr xiàng méi jiǎnchá. | P52: 还有十二项没检查。
A53: 52 | B53: empat | C53: sì | D53: 四 | E53: 四 (sì): empat | G53: Umum: sering dipakai native dalam percakapan sehari-hari. | H53: Ada empat mesin di lini ini. | I53: Zhè tiáo xiàn yǒu sì tái jī. | J53: 这条线有四台机。 | K53: Empat orang tidak hadir hari ini. | L53: Jīntiān yǒu sì ge rén méi lái. | M53: 今天有四个人没来。 | N53: Empat dikali dua sama dengan delapan. | O53: Sì chéng èr děngyú bā. | P53: 四乘二等于八。
A54: 53 | B54: empat belas | C54: shísì | D54: 十四 | E54: 十 (shí): sepuluh, 四 (sì): empat | G54: Umum: sering dipakai native dalam percakapan sehari-hari. | H54: Ada empat belas file di folder ini. | I54: Zhè ge wénjiànjiā lǐ yǒu shísì ge wénjiàn. | J54: 这个文件夹里有十四个文件。 | K54: Tanggal empat belas adalah hari libur. | L54: Shísì hào shì jiàrì. | M54: 十四号是假日。 | N54: Saya bekerja empat belas hari berturut-turut. | O54: Wǒ liánxù gōngzuò le shísì tiān. | P54: 我连续工作了十四天。
... A58: 57 | B58: End Face Inspection/Inspeksi Permukaan Ujung Serat | C58: duānmiàn jiǎnchá | D58: 端面检查 | E58: 端面 (duānmiàn): permukaan ujung (end face), 检查 (jiǎnchá): inspeksi | G58: Umum: sering dipakai native dalam percakapan sehari-hari. | H58: Lakukan end face inspection sebelum coupling. | I58: Ǒuhé qián jìnxíng duānmiàn jiǎnchá. | J58: 耦合前进行端面检查。 | K58: Hasil end face inspection ada yang tidak lolos. | L58: Duānmiàn jiǎnchá yǒu yìxiē bù hégé. | M58: 端面检查有一些不合格。 | N58: Mikroskop untuk end face inspection sudah dikalibrasi. | O58: Yòng yú duānmiàn jiǎnchá de xiǎnwēijìng yǐjīng jiàozhǔn le. | P58: 用于端面检查的显微镜已经校准了。
A59: 58 | B59: Februari | C59: èryuè | D59: 二月 | E59: 二 (èr): dua, 月 (yuè): bulan | F59: Pada kolom B tertulis "Fabruari" → seharusnya "Februari" | G59: Umum: sering dipakai native dalam percakapan sehari-hari. | H59: Proyek ini selesai pada bulan Februari. | I59: Zhè ge xiàngmù èryuè wánchéng. | J59: 这个项目二月完成。 | K59: Libur Imlek biasanya di bulan Februari. | L59: Chūnjié tōngcháng zài èryuè. | M59: 春节通常在二月。 | N59: Pelatihan dimulai Februari tahun depan. | O59: Míngnián èryuè kāishǐ péixùn. | P59: 明年二月开始培训。
A60: 59 | B60: Fiber splitting/Pemisahan Fiber | C60: fēnxiān | D60: 分纤 | E60: 分 (fēn): pisah, 纤 (xiān): serat / fiber, 分纤 (fēnxiān): pemisahan fiber | G60: Umum: sering dipakai native dalam percakapan sehari-hari. | H60: Fiber splitting harus hati-hati agar tidak patah. | I60: Fēnxiān yào xiǎoxīn, bié duàn le. | J60: 分纤要小心，别断了。 | K60: Hasil fiber splitting sudah dicek. | L60: Fēnxiān de jiéguǒ yǐjīng jiǎnchá le. | M60: 分纤的结果已经检查了。 | N60: Mesin fiber splitting sedang dipakai. | O60: Fēnxiān jī zhèng zài yòng. | P60: 分纤机正在用。
A61: 60 | B61: Fiber Stripping/Pengupasan Serat | C61: bāoxiān | D61: 剥纤 | E61: 剥 (bāo): kupas, 纤 (xiān): serat / fiber, 剥纤 (bāoxiān): pengupasan serat | F61: 剥 dibaca bāo (lisan) atau bō (formal); di pabrik umumnya bāo | G61: Umum: sering dipakai native dalam percakapan sehari-hari. | H61: Fiber stripping dilakukan sebelum pemotongan. | I61: Bāoxiān zài qiēduàn qián jìnxíng. | J61: 剥纤在切断前进行。 | K61: Gunakan alat fiber stripping yang tajam. | L61: Yòng jiānlì de bāoxiān qì. | M61: 用尖利的剥纤器。 | N61: Setelah fiber stripping, serat dibersihkan. | O61: Bāoxiān hòu, bǎ xiān qīngxǐ gānjìng. | P61: 剥纤后，把纤清洗干净。
A62: 61 | B62: Glue Injection/Injeksi Lem | C62: zhùjiāo | D62: 注胶 | E62: 注 (zhù): tuang / injeksi, 胶 (jiāo): lem, 注胶 (zhùjiāo): injeksi lem | G62: Umum: sering dipakai native dalam percakapan sehari-hari. | H62: Glue injection harus sesuai takaran. | I62: Zhùjiāo yào àn fènliàng jìnxíng. | J62: 注胶要按份量进行。 | K62: Mesin glue injection sedang dibersihkan. | L62: Zhùjiāo jī zhèng zài qīngxǐ. | M62: 注胶机正在清洗。 | N62: Setelah glue injection, produk dimasukkan oven. | O62: Zhùjiāo hòu, bǎ chǎnpǐn fàng jìn hōngxiāng. | P62: 注胶后，把产品放进烘箱。
A63: 62 | B63: Guru | C63: lǎoshī | D63: 老师 | E63: 老 (lǎo): tua / senior, 师 (shī): guru, 老师 (lǎoshī): guru | G63: Umum: sering dipakai native dalam percakapan sehari-hari. | H63: Dia guru bahasa Mandarin saya. | I63: Tā shì wǒ de Zhōngwén lǎoshī. | J63: 他是我的中文老师。 | K63: Guru itu sangat sabar. | L63: Nà wèi lǎoshī hěn yǒu nàixīn. | M63: 那位老师很有耐心。 | N63: Saya bertanya kepada guru. | O63: Wǒ wèn lǎoshī. | P63: 我问老师。
A64: 63 | B64: Halo | C64: nǐ hǎo | D64: 你好 | E64: 你 (nǐ): kamu, 好 (hǎo): baik | G64: Umum: sering dipakai native dalam percakapan sehari-hari. | H64: Halo, apa kabar? | I64: Nǐ hǎo, nǐ hǎo ma? | J64: 你好，你好吗？ | K64: Halo, selamat datang di pabrik. | L64: Nǐ hǎo, huānyíng lái dào gōngchǎng. | M64: 你好，欢迎来到工厂。 | N64: Halo, apakah ini Pak Wang? | O64: Nǐ hǎo, shì Wáng xiānsheng ma? | P64: 你好，是王先生吗？
A65: 64 | B65: Hari apa? | C65: jīntiān xīngqī jǐ? | D65: 今天星期几？ | E65: 今天 (jīntiān): hari ini, 星期 (xīngqī): minggu / hari, 几 (jǐ): berapa | G65: Umum: sering dipakai native dalam percakapan sehari-hari. | H65: Besok hari apa? | I65: Míngtiān xīngqī jǐ? | J65: 明天星期几？ | K65: Rapatnya hari apa? | L65: Huìyì shì xīngqī jǐ? | M65: 会议是星期几？ | N65: Hari ini hari apa? | O65: Jīntiān xīngqī jǐ? | P65: 今天星期几？
A66: 65 | B66: hari ini | C66: jīntiān | D66: 今天 | E66: 今天 (jīntiān): hari ini | G66: Umum: sering dipakai native dalam percakapan sehari-hari. | H66: Hari ini saya libur. | I66: Jīntiān wǒ xiūxi. | J66: 今天我休息。 | K66: Hari ini cuacanya panas. | L66: Jīntiān tiānqì hěn rè. | M66: 今天天气很热。 | N66: Hari ini target produksi tercapai. | O66: Jīntiān de shēngchǎn mùbiāo wánchéng le. | P66: 今天的生产目标完成了。
A67: 66 | B67: Hasilnya sama saja | C67: Jiéguǒ dōu yíyàng | D67: 结果都一样 | E67: 结果 (jiéguǒ): hasil, 都 (dōu): semua, 一样 (yíyàng): sama | G67: Umum: sering dipakai native dalam percakapan sehari-hari. | H67: Mau pakai merek A atau B, hasilnya sama saja. | I67: Yòng A pái háishì B pái, jiéguǒ dōu yíyàng. | J67: 用A牌还是B牌，结果都一样。 | K67: Dicek dua kali atau sekali, hasilnya sama saja. | L67: Jiǎnchá liǎng cì huòzhě yí cì, jiéguǒ dōu yíyàng. | M67: 检查两次或一次，结果都一样。 | N67: Pakai kertas atau digital, hasilnya sama saja. | O67: Yòng zhǐ háishì diànzǐ, jiéguǒ dōu yíyàng. | P67: 用纸还是电子，结果都一样。
A68: 67 | B68: I am okay/saya tidak apa-apa | C68: wǒ méi shì | D68: 我没事 | E68: 我 (wǒ): saya, 没事 (méi shì): tidak apa-apa | G68: Umum: sering dipakai native dalam percakapan sehari-hari. | H68: Saya tidak apa-apa, jangan khawatir. | I68: Wǒ méi shì, bié dānxīn. | J68: 我没事，别担心。 | K68: Saya tidak apa-apa, hanya sedikit lelah. | L68: Wǒ méi shì, zhǐshì yǒu diǎn lèi. | M68: 我没事，只是有点累。 | N68: Tadi saya jatuh, tapi saya tidak apa-apa. | O68: Gāngcái wǒ shuāidǎo le, dàn wǒ méi shì. | P68: 刚才我摔倒了，但我没事。
A69: 68 | B69: ini | C69: zhè / zhè gè | D69: 这 / 这个 | E69: 这 (zhè): ini, 个 (gè): kata penggolong umum | G69: Umum: sering dipakai native dalam percakapan sehari-hari. | H69: Ini milik saya. | I69: Zhè shì wǒ de. | J69: 这是我的。 | K69: Ini laporan yang kemarin. | L69: Zhè shì zuótiān de bàogào. | M69: 这是昨天的报告。 | N69: Ini harga yang benar. | O69: Zhè shì zhèngquè de jiàgé. | P69: 这是正确的价格。
A70: 69 | B70: ini apa? | C70: zhè shì shénme? | D70: 这是什么？ | E70: 这 (zhè): ini, 是 (shì): adalah, 什么 (shénme): apa | G70: Umum: sering dipakai native dalam percakapan sehari-hari. | H70: Ini apa? | I70: Zhè shì shénme? | J70: 这是什么？ | K70: Ini apa, kok warnanya merah? | L70: Zhè shì shénme, zěnme shì hóngsè de? | M70: 这是什么，怎么是红色的？ | N70: Ini apa di dalam kotak? | O70: Hézi lǐ de zhè shì shénme? | P70: 盒子里的这是什么？
A71: 70 | B71: Ini berapa? (menanyakan harga) | C71: zhè duōshao qián? | D71: 这多少钱？ | E71: 这 (zhè): ini, 多少 (duōshao): berapa, 钱 (qián): harga / uang | G71: Umum: sering dipakai native dalam percakapan sehari-hari. | H71: Ini berapa harganya? | I71: Zhè duōshao qián? | J71: 这多少钱？ | K71: Ini berapa, kok mahal sekali? | L71: Zhè duōshao qián, zěnme zhème guì? | M71: 这多少钱，怎么这么贵？ | N71: Saya mau beli ini, berapa? | O71: Wǒ xiǎng mǎi zhè ge, duōshao qián? | P71: 我想买这个，多少钱？
A72: 71 | B72: Ini saja? | C72: jiù zhè ge ma? | D72: 就这个吗？ | E72: 就 (jiù): hanya, 这个 (zhè ge): ini, 吗 (ma): partikel tanya | G72: Umum: sering dipakai native dalam percakapan sehari-hari. | H72: Mau pesan ini saja? | I72: Jiù yào zhè ge ma? | J72: 就要这个吗？ | K72: Belanjanya ini saja? | L72: Mǎi de jiù zhè xiē ma? | M72: 买的就这些吗？ | N72: Cukup ini saja? | O72: Jiù zhè ge gòu le ma? | P72: 就这个够了吗？
A73: 72 | B73: Inner shell cleaning/Pembersihan Selongsong Dalam | C73: nèiké qīngxǐ | D73: 内壳清洗 | E73: 内 (nèi): dalam, 壳 (ké): selongsong / cangkang, 清洗 (qīngxǐ): pembersihan / cuci | G73: Kurang umum: Istilah ini tidak baku di pabrik; cek istilah yang dipakai tim. | H73: Inner shell cleaning dilakukan sebelum assembly. | I73: Nèiké qīngxǐ zài zǔzhuāng qián jìnxíng. | J73: 内壳清洗在组装前进行。 | K73: Hasil inner shell cleaning harus bersih. | L73: Nèiké qīngxǐ de jiéguǒ yào gānjìng. | M73: 内壳清洗的结果要干净。 | N73: Mesin inner shell cleaning sudah diperbaiki. | O73: Nèiké qīngxǐ jī yǐjīng xiūlǐ hǎo le. | P73: 内壳清洗机已经修理好了。
... A76: 75 | B76: Jam berapa sekarang? | C76: xiànzài jǐ diǎn le? | D76: 现在几点了？ | E76: 现在 (xiànzài): sekarang, 几 (jǐ): berapa, 点 (diǎn): jam, 了 (le): partikel | G76: Umum: sering dipakai native dalam percakapan sehari-hari. | H76: Permisi, jam berapa sekarang? | I76: Qǐngwèn, xiànzài jǐ diǎn le? | J76: 请问，现在几点了？ | K76: Jam berapa sekarang, kita sudah telat? | L76: Xiànzài jǐ diǎn le, wǒmen chídào le ma? | M76: 现在几点了，我们迟到了吗？ | N76: Jam berapa sekarang? Rapat mulai jam tiga. | O76: Xiànzài jǐ diǎn le? Huìyì sān diǎn kāishǐ. | P76: 现在几点了？会议三点开始。
A77: 76 | B77: Januari | C77: yīyuè | D77: 一月 | E77: 一 (yī): satu, 月 (yuè): bulan | F77: Nama bulan = angka + 月 | G77: Umum (tulisan): Dipakai di tulisan/kalender; lisan sehari-hari lebih sering 一月 (sama) tapi tanggal biasanya dibaca 号. | H77: Kontrak baru mulai bulan Januari. | I77: Xīn hétóng yīyuè kāishǐ. | J77: 新合同一月开始。 | K77: Pabrik libur pada bulan Januari. | L77: Gōngchǎng yīyuè fàngjià. | M77: 工厂一月放假。 | N77: Laporan tahunan dibuat pada bulan Januari. | O77: Niándù bàogào yīyuè zhìzuò. | P77: 年度报告一月制作。
A78: 77 | B78: Juli | C78: qīyuè | D78: 七月 | E78: 七 (qī): tujuh, 月 (yuè): bulan | G78: Umum: sering dipakai native dalam percakapan sehari-hari. | H78: Produksi besar di bulan Juli. | I78: Qīyuè shēngchǎn hěn duō. | J78: 七月生产很多。 | K78: Libur panjang bulan Juli. | L78: Qīyuè yǒu cháng jià. | M78: 七月有长假。 | N78: Audit dilakukan Juli nanti. | O78: Qīyuè jìnxíng shěnjì. | P78: 七月进行审计。
A79: 78 | B79: Jumat | C79: xīngqīwǔ | D79: 星期五 | E79: 星期 (xīngqī): minggu / hari, 五 (wǔ): lima | G79: Umum: sering dipakai native dalam percakapan sehari-hari. | H79: Rapat mingguan hari Jumat. | I79: Měi zhōu de huìyì zài xīngqīwǔ. | J79: 每周的会议在星期五。 | K79: Saya pulang lebih awal hari Jumat. | L79: Xīngqīwǔ wǒ zǎo diǎn xià bān. | M79: 星期五我早点下班。 | N79: Laporan harus dikirim paling lambat hari Jumat. | O79: Bàogào zuì wǎn xīngqīwǔ yào fā chū. | P79: 报告最晚星期五要发出。
A80: 79 | B80: Juni | C80: liùyuè | D80: 六月 | E80: 六 (liù): enam, 月 (yuè): bulan | G80: Umum: sering dipakai native dalam percakapan sehari-hari. | H80: Kami mulai pelatihan bulan Juni. | I80: Wǒmen liùyuè kāishǐ péixùn. | J80: 我们六月开始培训。 | K80: Produksi naik sejak Juni. | L80: Cóng liùyuè qǐ, chǎnliàng zēngjiā le. | M80: 从六月起，产量增加了。 | N80: Liburan sekolah bulan Juni. | O80: Xuéxiào zài liùyuè fàngjià. | P80: 学校在六月放假。
A81: 80 | B81: kami | C81: wǒmen | D81: 我们 | E81: 我 (wǒ): saya, 们 (men): penanda jamak | G81: Umum: sering dipakai native dalam percakapan sehari-hari. | H81: Kami sudah selesai mengerjakannya. | I81: Wǒmen zuò wán le. | J81: 我们做完了。 | K81: Kami akan rapat jam dua. | L81: Wǒmen liǎng diǎn kāi huì. | M81: 我们两点开会。 | N81: Kami dari tim QC. | O81: Wǒmen shì zhìjiǎn tuánduì de. | P81: 我们是质检团队的。
A82: 81 | B82: Kamis | C82: xīngqīsì | D82: 星期四 | E82: 星期 (xīngqī): minggu / hari, 四 (sì): empat | G82: Umum: sering dipakai native dalam percakapan sehari-hari. | H82: Rapat diundur ke hari Kamis. | I82: Huìyì tuīchí dào xīngqīsì. | J82: 会议推迟到星期四。 | K82: Kamis depan saya cuti. | L82: Xià ge xīngqīsì wǒ xiūjià. | M82: 下个星期四我休假。 | N82: Kamis sore kita evaluasi. | O82: Xīngqīsì xiàwǔ wǒmen pínggū. | P82: 星期四下午我们评估。
A83: 82 | B83: kamu | C83: nǐ | D83: 你 | E83: 你 (nǐ): kamu | G83: Umum: sering dipakai native dalam percakapan sehari-hari. | H83: Kamu sudah makan? | I83: Nǐ chī fàn le ma? | J83: 你吃饭了吗？ | K83: Kamu mau ke mana? | L83: Nǐ yào qù nǎr? | M83: 你要去哪儿？ | N83: Kamu bisa membantu saya? | O83: Nǐ néng bāng wǒ ma? | P83: 你能帮我吗？
A84: 83 | B84: kamu hebat | C84: nǐ zhēn bàng | D84: 你真棒 | E84: 你 (nǐ): kamu, 真 (zhēn): sungguh, 棒 (bàng): hebat / keren | F84: Pujian santai, sangat umum | G84: Umum: sering dipakai native dalam percakapan sehari-hari. | H84: Kamu hebat, hasilnya bagus sekali! | I84: Nǐ zhēn bàng, jiéguǒ hěn hǎo! | J84: 你真棒，结果很好！ | K84: Kerjaanmu hebat, terus semangat! | L84: Nǐ de gōngzuò zhēn bàng, jiāyóu! | M84: 你的工作真棒，加油！ | N84: Presentasimu hebat sekali. | O84: Nǐ de bàogào zuò de zhēn bàng. | P84: 你报告做得真棒。
A85: 84 | B85: kamu Jago | C85: nǐ hěn lìhai | D85: 你很厉害 | E85: 你 (nǐ): kamu, 很 (hěn): sangat, 厉害 (lìhai): jago / hebat | F85: 厉害 = jago / hebat (skill) | G85: Umum: sering dipakai native dalam percakapan sehari-hari. | H85: Kamu jago sekali memperbaiki mesin. | I85: Nǐ xiūlǐ jī qì hěn lìhai. | J85: 你修理机器很厉害。 | K85: Kamu jago bahasa Mandarin ya? | L85: Nǐ Hànyǔ hěn lìhai ba? | M85: 你汉语很厉害吧？ | N85: Kamu jago sekali di bidang ini. | O85: Nǐ zài zhè ge lǐngyù hěn lìhai. | P85: 你在这个领域很厉害。
A86: 85 | B86: Kamu kaya | C86: nǐ hěn yǒuqián | D86: 你很有钱 | E86: 你 (nǐ): kamu, 很 (hěn): sangat, 有钱 (yǒuqián): kaya / punya uang | G86: Umum (hati-hati): Bisa dipakai, tetapi terdengar seperti sindiran atau pertanyaan pribadi; hindari di percakapan biasa. | H86: Kamu kaya ya, rumahmu besar. | I86: Nǐ hěn yǒuqián ba, nǐ de fángzi hěn dà. | J86: 你很有钱吧，你的房子很大。 | K86: Dia bilang kamu kaya. | L86: Tā shuō nǐ hěn yǒuqián. | M86: 他说你很有钱。 | N86: Walaupun kamu kaya, kamu tetap rendah hati. | O86: Suīrán nǐ hěn yǒuqián, dàn hěn qiānxū. | P86: 虽然你很有钱，但很谦虚。
A87: 86 | B87: kamu pandai | C87: nǐ hěn nénggàn | D87: 你很能干 | E87: 你 (nǐ): kamu, 很 (hěn): sangat, 能干 (nénggàn): pandai / cakap bekerja | F87: 能干 = pandai/cakap dalam bekerja | G87: Cukup umum: Dipakai untuk memuji kemampuan kerja; lebih lazim 你很厉害 atau 你很能干. | H87: Kamu pandai bekerja dengan tim. | I87: Nǐ hěn nénggàn, néng hé tuánduì hézuò. | J87: 你很能干，能和团队合作。 | K87: Kamu pandai sekali mengatur jadwal. | L87: Nǐ ānpái rìchéng hěn nénggàn. | M87: 你安排日程很能干。 | N87: Dia pandai memperbaiki mesin. | O87: Tā hěn nénggàn, huì xiū jī qì. | P87: 他很能干，会修机器。
A88: 87 | B88: kamu pintar | C88: nǐ hěn cōngmíng | D88: 你很聪明 | E88: 你 (nǐ): kamu, 很 (hěn): sangat, 聪明 (cōngmíng): pintar | G88: Umum: sering dipakai native dalam percakapan sehari-hari. | H88: Kamu pintar, cepat sekali belajarnya. | I88: Nǐ hěn cōngmíng, xuéxí hěn kuài. | J88: 你很聪明，学习很快。 | K88: Anak itu pintar sekali. | L88: Nà ge háizi hěn cōngmíng. | M88: 那个孩子很聪明。 | N88: Kamu pintar menyelesaikan masalah ini. | O88: Nǐ hěn cōngmíng, jiějué le zhè ge wèntí. | P88: 你很聪明，解决了这个问题。
A89: 88 | B89: Kapan? | C89: shénme shíhou? | D89: 什么时候？ | E89: 什么 (shénme): apa, 时候 (shíhou): waktu | G89: Umum: sering dipakai native dalam percakapan sehari-hari. | H89: Kita mulai kapan? | I89: Wǒmen shénme shíhou kāishǐ? | J89: 我们什么时候开始？ | K89: Kapan laporannya selesai? | L89: Bàogào shénme shíhou wán? | M89: 报告什么时候完？ | N89: Kapan kamu pulang? | O89: Nǐ shénme shíhou huí jiā? | P89: 你什么时候回家？
A90: 89 | B90: ke mana? | C90: qù nǎr? | D90: 去哪儿？ | E90: 去 (qù): pergi, 哪儿 (nǎr): mana | G90: Umum: sering dipakai native dalam percakapan sehari-hari. | H90: Kamu mau pergi ke mana? | I90: Nǐ yào qù nǎr? | J90: 你要去哪儿？ | K90: Mau ke mana sekarang? | L90: Xiànzài qù nǎr? | M90: 现在去哪儿？ | N90: Ke mana perginya minggu depan? | O90: Xià ge xīngqī qù nǎr? | P90: 下个星期去哪儿？
A91: 90 | B91: Kecil | C91: xiǎo | D91: 小 | E91: 小 (xiǎo): kecil | F91: Pinyin dilengkapi tanda nada | G91: Umum: sering dipakai native dalam percakapan sehari-hari. | H91: Ukuran produk ini kecil. | I91: Zhè ge chǎnpǐn de chǐcun hěn xiǎo. | J91: 这个产品的尺寸很小。 | K91: Anak itu masih kecil. | L91: Nà ge háizi hái hěn xiǎo. | M91: 那个孩子还很小。 | N91: Ruangannya terlalu kecil. | O91: Fángjiān tài xiǎo le. | P91: 房间太小了。
A92: 91 | B92: lama | C92: jiù | D92: 旧 | E92: 旧 (jiù): lama / bekas (untuk barang) | G92: Umum (barang): Untuk barang, 旧 wajar. Untuk durasi ("sudah lama"), native pakai 很久 (hěn jiǔ) atau 长时间. | H92: Mesin ini sudah lama, sering rusak. | I92: Zhè tái jī hěn jiù le, chángcháng huài. | J92: 这台机很旧了，常常坏。 | K92: Baju ini sudah lama, tapi masih bagus. | L92: Zhè jiàn yīfu hěn jiù le, dàn hái hěn hǎo. | M92: 这件衣服很旧了，但还很好。 | N92: Kertas lama dipisahkan dari yang baru. | O92: Jiù zhǐ hé xīn zhǐ fēnkāi fàng. | P92: 旧纸和新纸分开放。
A93: 92 | B93: lima | C93: wǔ | D93: 五 | E93: 五 (wǔ): lima | G93: Umum: sering dipakai native dalam percakapan sehari-hari. | H93: Ada lima orang di shift pagi. | I93: Zǎo bān yǒu wǔ gè rén. | J93: 早班有五个人。 | K93: Lima tambah tiga sama dengan delapan. | L93: Wǔ jiā sān děngyú bā. | M93: 五加三等于八。 | N93: Lima menit lagi rapat dimulai. | O93: Wǔ fēnzhōng hòu huìyì kāishǐ. | P93: 五分钟后会议开始。
A94: 93 | B94: lima belas | C94: shíwǔ | D94: 十五 | E94: 十 (shí): sepuluh, 五 (wǔ): lima | G94: Umum: sering dipakai native dalam percakapan sehari-hari. | H94: Ada lima belas kotak di gudang. | I94: Cāngkù lǐ yǒu shíwǔ ge xiāngzi. | J94: 仓库里有十五个箱子。 | K94: Lima belas menit lagi istirahat. | L94: Shíwǔ fēnzhōng hòu xiūxi. | M94: 十五分钟后休息。 | N94: Tanggal lima belas gajian. | O94: Shíwǔ hào fā gōngzī. | P94: 十五号发工资。
A95: 94 | B95: Lusa | C95: hòutiān | D95: 后天 | E95: 后 (hòu): setelah, 天 (tiān): hari, 后天 (hòutiān): lusa | G95: Umum: sering dipakai native dalam percakapan sehari-hari. | H95: Lusa saya ke Shenzhen. | I95: Hòutiān wǒ qù Shēnzhèn. | J95: 后天我去深圳。 | K95: Laporannya lusa baru jadi. | L95: Bàogào hòutiān cái wánchéng. | M95: 报告后天才完成。 | N95: Lusa kita evaluasi hasilnya. | O95: Hòutiān wǒmen pínggū jiéguǒ. | P95: 后天我们评估结果。
A96: 95 | B96: maaf | C96: duìbùqǐ | D96: 对不起 | E96: 对不起 (duìbuqǐ): maaf | G96: Umum: sering dipakai native dalam percakapan sehari-hari. | H96: Maaf, saya terlambat. | I96: Duìbuqǐ, wǒ chídào le. | J96: 对不起，我迟到了。 | K96: Maaf, saya tidak bisa datang. | L96: Duìbuqǐ, wǒ bù néng lái. | M96: 对不起，我不能来。 | N96: Maaf sudah menunggu lama. | O96: Duìbuqǐ, ràng nǐ děng le hěn jiǔ. | P96: 对不起，让你等了很久。
A97: 96 | B97: Mahal | C97: guì | D97: 贵 | E97: 贵 (guì): mahal | G97: Umum: sering dipakai native dalam percakapan sehari-hari. | H97: Harga mesin ini mahal sekali. | I97: Zhè tái jī de jiàgé hěn guì. | J97: 这台机的价格很贵。 | K97: Sayur di pasar sekarang mahal. | L97: Xiànzài shìchǎng de cài hěn guì. | M97: 现在市场的菜很贵。 | N97: Barang ini terlalu mahal untuk kita. | O97: Zhè ge dōngxi duì wǒmen lái shuō tài guì le. | P97: 这个东西对我们来说太贵了。
A98: 97 | B98: Maret | C98: sānyuè | D98: 三月 | E98: 三 (sān): tiga, 月 (yuè): bulan | G98: Umum: sering dipakai native dalam percakapan sehari-hari. | H98: Kontrak diperpanjang sampai Maret. | I98: Hétóng yánchí dào sānyuè. | J98: 合同延长到三月。 | K98: Pelatihan selesai bulan Maret. | L98: Péixùn sānyuè wánchéng. | M98: 培训三月完成。 | N98: Mulai Maret kita pakai sistem baru. | O98: Cóng sānyuè qǐ, wǒmen yòng xīn xìtǒng. | P98: 从三月起，我们用新系统。
A99: 98 | B99: masih ada | C99: Hái yǒu | D99: 还有 | E99: 还 (hái): masih, 有 (yǒu): ada | G99: Umum: sering dipakai native dalam percakapan sehari-hari. | H99: Masih ada stok kertas? | I99: Hái yǒu zhǐ de kùcún ma? | J99: 还有纸的库存吗？ | K99: Masih ada waktu sebelum rapat. | L99: Kāihuì qián hái yǒu shíjiān. | M99: 开会前还有时间。 | N99: Masih ada beberapa barang yang belum dikirim. | O99: Hái yǒu yìxiē dōngxi méi fāchū. | P99: 还有一些东西没发出。
A100: 99 | B100: Masih belum paham | C100: hái méi míngbái | D100: 还没明白 | E100: 还 (hái): masih, 没 (méi): belum, 明白 (míngbái): paham | G100: Umum: sering dipakai native dalam percakapan sehari-hari. | H100: Saya masih belum paham caranya. | I100: Wǒ hái méi míngbái zěnme zuò. | J100: 我还没明白怎么做。 | K100: Maaf, saya masih belum paham. | L100: Duìbuqǐ, wǒ hái méi míngbái. | M100: 对不起，我还没明白。 | N100: Dia masih belum paham instruksinya. | O100: Tā hái méi míngbái zhǐshì. | P100: 他还没明白指示。
A101: 100 | B101: masih kurang begitu paham | C101: bú tài míngbái | D101: 不太明白 | E101: 不 (bú): tidak, 太 (tài): terlalu / begitu, 明白 (míngbái): paham | G101: Umum: sering dipakai native dalam percakapan sehari-hari. | H101: Saya masih kurang begitu paham tentang prosesnya. | I101: Wǒ duì zhè ge liúchéng bú tài míngbái. | J101: 我对这个流程不太明白。 | K101: Penjelasannya masih kurang begitu paham. | L101: Jiěshì wǒ hái bú tài míngbái. | M101: 解释我还不太明白。 | N101: Saya kurang begitu paham angka ini. | O101: Wǒ bú tài míngbái zhè xiē shùzì. | P101: 我不太明白这些数字。
A102: 101 | B102: mati | C102: guān | D102: 关 | E102: 关 (guān): mematikan / menutup | F102: Contoh: 关机 (guānjī) matikan mesin, 关灯 (guān dēng) matikan lampu | G102: Umum: sering dipakai native dalam percakapan sehari-hari. | H102: Tolong matikan mesinnya. | I102: Qǐng guān diào jī qì. | J102: 请关掉机器。 | K102: Matikan lampu, tolong. | L102: Qǐng guān dēng. | M102: 请关灯。 | N102: Mesin itu mati tiba-tiba. | O102: Nà tái jī tūrán guān le. | P102: 那台机突然关了。
A103: 102 | B103: mau | C103: yào | D103: 要 | E103: 要 (yào): mau / ingin | G103: Umum: sering dipakai native dalam percakapan sehari-hari. | H103: Saya mau kopi. | I103: Wǒ yào kāfēi. | J103: 我要咖啡。 | K103: Kamu mau pulang sekarang? | L103: Nǐ xiànzài yào huí qù ma? | M103: 你现在要回去吗？ | N103: Saya mau belajar bahasa Mandarin. | O103: Wǒ yào xué Zhōngwén. | P103: 我要学中文。
A104: 103 | B104: Mei | C104: wǔyuè | D104: 五月 | E104: 五 (wǔ): lima, 月 (yuè): bulan | G104: Umum: sering dipakai native dalam percakapan sehari-hari. | H104: Pameran besar diadakan bulan Mei. | I104: Dà zhǎnlǎn zài wǔyuè jǔxíng. | J104: 大展览在五月举行。 | K104: Produksi bulan Mei naik. | L104: Wǔyuè de chǎnliàng zēngjiā le. | M104: 五月的产量增加了。 | N104: Liburan Mei sudah dekat. | O104: Wǔyuè de jiàqī kuài dào le. | P104: 五月的假期快到了。
A105: 104 | B105: mengerti | C105: dǒng | D105: 懂 | E105: 懂 (dǒng): mengerti | G105: Umum: sering dipakai native dalam percakapan sehari-hari. | H105: Saya mengerti maksudmu. | I105: Wǒ dǒng nǐ de yìsi. | J105: 我懂你的意思。 | K105: Kamu mengerti instruksinya? | L105: Nǐ dǒng zhǐshì ma? | M105: 你懂指示吗？ | N105: Dia tidak mengerti bahasa Mandarin. | O105: Tā bù dǒng Zhōngwén. | P105: 他不懂中文。
A106: 105 | B106: mereka | C106: tāmen | D106: 他们 / 她们 | E106: 他 (tā): dia (laki-laki), 她 (tā): dia (perempuan), 们 (men): penanda jamak | G106: Umum: sering dipakai native dalam percakapan sehari-hari. | H106: Mereka sudah pulang. | I106: Tāmen yǐjīng huí jiā le. | J106: 他们已经回家了。 | K106: Mereka operator baru. | L106: Tāmen shì xīn cāozuòyuán. | M106: 他们是新操作员。 | N106: Tolong beritahu mereka. | O106: Qǐng gàosu tāmen. | P106: 请告诉他们。
A107: 106 | B107: Minggu | C107: xīngqīrì / xīngqītiān | D107: 星期日 / 星期天 | E107: 星期 (xīngqī): minggu / hari, 日 (rì) / 天 (tiān): hari / matahari | F107: Bisa juga 周日 (zhōurì), 周 = singkatan 星期 | G107: Umum: 星期天 lebih lazim diucapkan daripada 星期日 (tulisan/formal). | H107: Hari Minggu kita libur. | I107: Xīngqītiān wǒmen xiūxi. | J107: 星期天我们休息。 | K107: Saya kerja sampai hari Minggu. | L107: Wǒ gōngzuò dào xīngqītiān. | M107: 我工作到星期天。 | N107: Minggu ini pesanan sangat banyak. | O107: Zhè ge xīngqī dìngdān hěn duō. | P107: 这个星期订单很多。
A108: 107 | B108: minggu depan | C108: xià ge xīngqī | D108: 下个星期 | E108: 下 (xià): berikutnya, 个 (gè): kata penggolong, 星期 (xīngqī): minggu | G108: Umum: sering dipakai native dalam percakapan sehari-hari. | H108: Minggu depan saya cuti. | I108: Xià ge xīngqī wǒ xiūjià. | J108: 下个星期我休假。 | K108: Kita rapat minggu depan. | L108: Wǒmen xià ge xīngqī kāi huì. | M108: 我们下个星期开会。 | N108: Laporan minggu depan harus selesai. | O108: Xià ge xīngqī de bàogào yào wánchéng. | P108: 下个星期的报告要完成。
A109: 108 | B109: Mohon tunggu sebentar | C109: Qǐng shāo děng | D109: 请稍等 | E109: 请 (qǐng): mohon, 稍 (shāo): sedikit, 等 (děng): tunggu | G109: Umum (sopan): Sopan, sering dipakai di layanan/kantor. Di percakapan biasa cukup 等一下. | H109: Mohon tunggu sebentar, saya cek dulu. | I109: Qǐng shāo děng, wǒ xiān jiǎnchá yíxià. | J109: 请稍等，我先检查一下。 | K109: Mohon tunggu sebentar di sini. | L109: Qǐng zài zhèr shāo děng. | M109: 请在这儿稍等。 | N109: Mohon tunggu sebentar, pimpinan sedang rapat. | O109: Qǐng shāo děng, lǐngdǎo zhèng zài kāi huì. | P109: 请稍等，领导正在开会。
A110: 109 | B110: Murah | C110: piányi | D110: 便宜 | E110: 便宜 (piányi): murah | G110: Umum: sering dipakai native dalam percakapan sehari-hari. | H110: Harga di toko ini murah. | I110: Zhè jiā diàn de jiàgé hěn piányi. | J110: 这家店的价格很便宜。 | K110: Barang ini murah dan bagus. | L110: Zhè ge dōngxi piányi yòu hǎo. | M110: 这个东西便宜又好。 | N110: Saya cari barang yang murah. | O110: Wǒ zhǎo piányi de dōngxi. | P110: 我找便宜的东西。
A111: 110 | B111: Murid | C111: xuésheng | D111: 学生 | E111: 学 (xué): belajar, 生 (shēng): orang yang, 学生 (xuésheng): murid / pelajar | G111: Umum: sering dipakai native dalam percakapan sehari-hari. | H111: Murid saya sudah bisa berbicara Mandarin. | I111: Wǒ de xuésheng yǐjīng huì shuō Zhōngwén le. | J111: 我的学生已经会说中文了。 | K111: Murid itu rajin sekali. | L111: Nà ge xuésheng hěn qínfèn. | M111: 那个学生很勤奋。 | N111: Murid-murid sedang belajar di kelas. | O111: Xuéshengmen zài jiàoshì lǐ xuéxí. | P111: 学生们在教室里学习。
A112: 111 | B112: Nama saya | C112: wǒ jiào …… | D112: 我叫…… | E112: 我 (wǒ): saya, 叫 (jiào): bernama / dipanggil | F112: Ganti …… dengan nama kamu | G112: Umum: sering dipakai native dalam percakapan sehari-hari. | H112: Nama saya Lin. | I112: Wǒ jiào Lín. | J112: 我叫林。 | K112: Nama saya Lin, saya dari bagian QC. | L112: Wǒ jiào Lín, wǒ shì zhìjiǎn bù de. | M112: 我叫林，我是质检部的。 | N112: Nama saya Lin, senang bertemu Anda. | O112: Wǒ jiào Lín, hěn gāoxìng rènshi nín. | P112: 我叫林，很高兴认识您。
A113: 112 | B113: nama setiap station di PIC | C113: gègè gōngwèi de míngchēng | D113: 各个工位的名称 | E113: 各个 (gègè): setiap, 工位 (gōngwèi): stasiun kerja / pos, 的 (de): dari/milik, 名称 (míngchēng): nama | G113: Kurang umum: Kata "station" dan "PIC" bukan istilah native; lebih wajar 各工位名称 (nama tiap stasiun kerja). | H113: Tolong cek nama setiap station di PIC. | I113: Qǐng jiǎnchá měi ge gōngwèi de míngchēng. | J113: 请检查每个工位的名称。 | K113: Nama setiap station harus dicatat. | L113: Měi ge gōngwèi de míngchēng yào jìlù. | M113: 每个工位的名称要记录。 | N113: Saya perlu daftar nama setiap station. | O113: Wǒ xūyào měi ge gōngwèi de míngchēng qīngdān. | P113: 我需要每个工位的名称清单。
A114: 113 | B114: Negara | C114: guójiā | D114: 国家 | E114: 国 (guó): negara, 家 (jiā): rumah / keluarga, 国家 (guójiā): negara | G114: Umum: sering dipakai native dalam percakapan sehari-hari. | H114: Negara mana yang kamu kunjungi? | I114: Nǐ qù guò nǎ ge guójiā? | J114: 你去过哪个国家？ | K114: Negara ini besar. | L114: Zhè ge guójiā hěn dà. | M114: 这个国家很大。 | N114: Setiap negara punya aturan sendiri. | O114: Měi ge guójiā dōu yǒu zìjǐ de guīdìng. | P114: 每个国家都有自己的规定。
A115: 114 | B115: NG/reject | C115: bùliángpǐn | D115: 不良品 | E115: 不 (bù): tidak, 良 (liáng): baik, 品 (pǐn): barang (barang cacat/reject) | G115: Umum di pabrik: 不良品 dipakai di pabrik untuk NG/reject. | H115: Produk NG harus dipisahkan. | I115: Bùliángpǐn yào fēnkāi fàng. | J115: 不良品要分开放。 | K115: Jumlah NG hari ini sedikit. | L115: Jīntiān de bùliángpǐn hěn shǎo. | M115: 今天的不良品很少。 | N115: Barang reject dikembalikan ke gudang. | O115: Bùliángpǐn tuì huí cāngkù. | P115: 不良品退回仓库。
A116: 115 | B116: November | C116: shíyīyuè | D116: 十一月 | E116: 十一 (shíyī): sebelas, 月 (yuè): bulan | G116: Umum: sering dipakai native dalam percakapan sehari-hari. | H116: Rapat tahunan diadakan bulan November. | I116: Niándù huìyì zài shíyīyuè jǔxíng. | J116: 年度会议在十一月举行。 | K116: Target November sudah tercapai. | L116: Shíyīyuè de mùbiāo yǐjīng dádào le. | M116: 十一月的目标已经达到了。 | N116: Proyek dimulai November tahun lalu. | O116: Qùnián shíyīyuè kāishǐ de xiàngmù. | P116: 去年十一月开始的项目。
A117: 116 | B117: nyala | C117: kāi | D117: 开 | E117: 开 (kāi): menyalakan / membuka | F117: Contoh: 开机 (kāijī) nyalakan mesin, 开灯 (kāi dēng) nyalakan lampu | G117: Umum: sering dipakai native dalam percakapan sehari-hari. | H117: Tolong nyalakan lampunya. | I117: Qǐng kāi dēng. | J117: 请开灯。 | K117: Mesin sudah nyala. | L117: Jī qì yǐjīng kāi le. | M117: 机器已经开了。 | N117: Nyalakan komputernya, tolong. | O117: Qǐng kāi diànnǎo. | P117: 请开电脑。
A118: 117 | B118: OK/pass/lolos | C118: hégé | D118: 合格 | E118: 合 (hé): sesuai, 格 (gé): standar (lolos/memenuhi standar) | G118: Umum di pabrik: 合格 dipakai di pabrik untuk pass/lolos. | H118: Hasil tes ini OK, lolos. | I118: Zhè cì cèshì jiéguǒ hégé. | J118: 这次测试结果合格。 | K118: Produk ini lolos QC. | L118: Zhè ge chǎnpǐn tōngguò zhìjiǎn, hégé le. | M118: 这个产品通过质检，合格了。 | N118: Semua produk shift pagi OK. | O118: Zǎo bān de chǎnpǐn dōu hégé. | P118: 早班的产品都合格。
A119: 118 | B119: Oktober | C119: shíyuè | D119: 十月 | E119: 十 (shí): sepuluh, 月 (yuè): bulan | G119: Umum: sering dipakai native dalam percakapan sehari-hari. | H119: Produksi bulan Oktober naik. | I119: Shíyuè de chǎnliàng zēngjiā le. | J119: 十月的产量增加了。 | K119: Libur Oktober sudah dekat. | L119: Shíyuè de jiàqī kuài dào le. | M119: 十月的假期快到了。 | N119: Audit besar diadakan Oktober. | O119: Shíyuè jǔxíng dà xíng shěnjì. | P119: 十月举行大型审计。
...
